yaclipy_tools/__about__.py
yaclipy_tools/__init__.py
yaclipy_tools/all.py
yaclipy_tools/commands.py
yaclipy_tools/curl.py
yaclipy_tools/docker.py
yaclipy_tools/ffmpeg.py
yaclipy_tools/firebase.py
yaclipy_tools/gcloud.py
yaclipy_tools/git.py
yaclipy_tools/gpg.py
yaclipy_tools/graphviz.py
yaclipy_tools/grep.py
yaclipy_tools/kubectl.py
yaclipy_tools/md5.py
yaclipy_tools/mio.py
yaclipy_tools/nginx.py
yaclipy_tools/openssl.py
yaclipy_tools/shasum.py
yaclipy_tools/singleton.py
yaclipy_tools/sys_tool.py
yaclipy_tools/proc_task/__init__.py
yaclipy_tools/proc_task/echo.py
yaclipy_tools/proc_task/input.py
yaclipy_tools/proc_task/lines.py
yaclipy_tools/proc_task/log.py
yaclipy_tools/proc_task/plugin.py
yaclipy_tools/proc_task/proc_task.py
yaclipy_tools/proc_task/watch.py
yaclipy_tools-0.10.1.dist-info/METADATA
yaclipy_tools-0.10.1.dist-info/WHEEL
yaclipy_tools-0.10.1.dist-info/licenses/LICENSE.txt
yaclipy_tools-0.10.1.dist-info/RECORD
