Metadata-Version: 2.1
Name: yaclipy-tools
Version: 0.10.1
Summary: An extensible, asyncio interface to subprocesses, plus a set of wrappers around common system tools that works well with yaclipy
Project-URL: Documentation, https://github.com/aaron-fl/yaclipy_tools#readme
Project-URL: Issues, https://github.com/aaron-fl/yaclipy_tools/issues
Project-URL: Source, https://github.com/aaron-fl/yaclipy_tools
Author-email: Aaron <aaron@framelunch.jp>
License-Expression: MIT
License-File: LICENSE.txt
Classifier: Development Status :: 4 - Beta
Classifier: Environment :: Console
Classifier: Framework :: AsyncIO
Classifier: Intended Audience :: Developers
Classifier: Natural Language :: English
Classifier: Programming Language :: Python
Classifier: Programming Language :: Python :: 3.7
Classifier: Programming Language :: Python :: 3.8
Classifier: Programming Language :: Python :: 3.9
Classifier: Programming Language :: Python :: 3.10
Classifier: Programming Language :: Python :: 3.11
Classifier: Programming Language :: Python :: Implementation :: CPython
Classifier: Programming Language :: Python :: Implementation :: PyPy
Classifier: Topic :: Software Development
Classifier: Topic :: Software Development :: Build Tools
Requires-Python: >=3.7
Requires-Dist: print-ext>=2.1.1
Requires-Dist: yaclipy>=1.1.1
